{
  "Number": 410,
  "Title": "Thy Broken Body, Gracious Lord",
  "Author": null,
  "Copyright": "PublicDomain",
  "CcliNumber": null,
  "Stanzas": [
    {
      "Lines": [
        "Thy broken body, gracious Lord,",
        "Is shadowed by this broken bread;",
        "The wine which in this cup is poured,",
        "Points to the blood which Thou hast shed."
      ],
      "Reference": {
        "Type": "Verse",
        "Number": 1
      }
    },
    {
      "Lines": [
        "And while we meet together thus,",
        "We show that we are one in Thee;",
        "Thy precious blood was shed for us,",
        "Thy death, O Lord, hast set us free!"
      ],
      "Reference": {
        "Type": "Verse",
        "Number": 2
      }
    },
    {
      "Lines": [
        "We have one hope that Thou wilt come,",
        "Thee in the air we wait to see;",
        "When Thou wilt give Thy saints a home,",
        "And we shall ever reign with Thee."
      ],
      "Reference": {
        "Type": "Verse",
        "Number": 3
      }
    }
  ],
  "StanzaOrder": [
    "Verse 1",
    "Verse 2",
    "Verse 3"
  ]
}